{
  "id": "1476",
  "name": "one leg squat",
  "slug": "one-leg-squat",
  "primaryMuscles": [
    "glutes",
    "quads"
  ],
  "secondaryMuscles": [
    "quads",
    "hamstrings",
    "calves"
  ],
  "equipment": [
    "bodyweight"
  ],
  "difficulty": "beginner",
  "trainingStyles": [
    "calisthenics"
  ],
  "bodyRegion": "legs",
  "instructions": [
    "Stand with your feet shoulder-width apart.",
    "Extend one leg forward, keeping it off the ground.",
    "Bend your standing leg and lower your body down as if sitting back into a chair.",
    "Keep your chest up and your back straight.",
    "Push through your heel to return to the starting position.",
    "Repeat with the other leg.",
    "Stand with your feet shoulder-width apart. Extend one leg forward, keeping it off the ground. Bend your standing leg and lower your body down as if sitting back into a chair. Keep your chest up and your back straight. Push through your heel to return to the starting position. Repeat with the other leg."
  ],
  "media": {
    "thumbnail": "/media/exercises/images/1476-C31LMnP.jpg",
    "hero": "/media/exercises/gifs/1476-C31LMnP.gif",
    "animation": "/media/exercises/gifs/1476-C31LMnP.gif",
    "gallery": [
      "/media/exercises/images/1476-C31LMnP.jpg",
      "/media/exercises/gifs/1476-C31LMnP.gif"
    ]
  },
  "sexModelSupport": [
    "male",
    "female"
  ],
  "conditionNotes": [
    {
      "conditionId": "scoliosis",
      "suitability": "suitable",
      "note": "Keep load symmetrical and stop at positions that create sharp pain or twisting."
    },
    {
      "conditionId": "arthritis",
      "suitability": "suitable",
      "note": "Use pain-free range of motion, slower tempo, and lighter progressions when joints feel irritated."
    },
    {
      "conditionId": "osteoporosis",
      "suitability": "suitable",
      "note": "Weight-bearing resistance exercises are beneficial for bone density when load is appropriate."
    },
    {
      "conditionId": "low_back_pain",
      "suitability": "suitable",
      "note": "Maintain neutral spine and avoid positions that aggravate the lower back."
    },
    {
      "conditionId": "hypertension",
      "suitability": "suitable",
      "note": "Maintain consistent breathing throughout. Avoid breath-holding."
    },
    {
      "conditionId": "diabetes",
      "suitability": "suitable",
      "note": "Both aerobic and resistance training improve insulin sensitivity. Monitor blood sugar before, during, and after sessions. Have a fast-acting carb available."
    },
    {
      "conditionId": "parkinsons",
      "suitability": "caution",
      "note": "Single-leg or balance-intensive variations increase fall risk. Use support or a seated alternative."
    },
    {
      "conditionId": "hypermobility",
      "suitability": "suitable",
      "note": "Focus on muscle co-contraction and joint stability. Avoid locking out joints passively."
    },
    {
      "conditionId": "pregnancy_postpartum",
      "suitability": "suitable",
      "note": "Functional patterns are generally safe. Prioritize pelvic floor awareness and avoid Valsalva."
    },
    {
      "conditionId": "rehab",
      "suitability": "suitable",
      "note": "Start light with higher reps and shorter ROM. Progress load gradually as pain-free capacity increases."
    }
  ],
  "movementPattern": "squat",
  "tags": [
    "upper legs",
    "glutes"
  ],
  "regressions": [],
  "progressions": [],
  "related": [],
  "provenance": {
    "primarySource": "exercise-dataset",
    "mergedSources": [
      "exercise-dataset"
    ],
    "rawIds": [
      "1476"
    ],
    "notes": []
  },
  "conditions": {
    "scoliosis": "suitable",
    "arthritis": "suitable",
    "osteoporosis": "suitable",
    "low_back_pain": "suitable",
    "hypertension": "suitable",
    "diabetes": "suitable",
    "parkinsons": "caution",
    "hypermobility": "suitable",
    "pregnancy_postpartum": "suitable",
    "rehab": "suitable"
  }
}